networkx_viewer/__init__.py
networkx_viewer/autocomplete_entry.py
networkx_viewer/graph_canvas.py
networkx_viewer/tests.py
networkx_viewer/tokens.py
networkx_viewer/viewer.py
networkx_viewer-0.3.1.dist-info/LICENSE.txt
networkx_viewer-0.3.1.dist-info/METADATA
networkx_viewer-0.3.1.dist-info/WHEEL
networkx_viewer-0.3.1.dist-info/top_level.txt
networkx_viewer-0.3.1.dist-info/RECORD
