Metadata-Version: 2.1
Name: networkx-viewer
Version: 0.3.1
Summary: Interactive viewer for networkx graphs.
Home-page: http://github.com/jsexauer/networkx_viewer
Author: Jason Sexauer
Author-email: genericcarbonlifeform@gmail.com
License: LICENSE.txt
Keywords: networkx,topology,graph theory
Platform: UNKNOWN
Classifier: Development Status :: 4 - Beta
Classifier: Topic :: Scientific/Engineering :: Mathematics
Classifier: Topic :: Scientific/Engineering :: Visualization
Classifier: Natural Language :: English
Classifier: License :: OSI Approved :: GNU General Public License (GPL)
Requires-Python: >3.5
License-File: LICENSE.txt
Requires-Dist: networkx (>=2.2)
